qfadf/__init__.py
qfadf/bootstrap.py
qfadf/core.py
qfadf/critical_values.py
qfadf/utils.py
qfadf-1.0.0.dist-info/LICENSE
qfadf-1.0.0.dist-info/METADATA
qfadf-1.0.0.dist-info/WHEEL
qfadf-1.0.0.dist-info/top_level.txt
qfadf-1.0.0.dist-info/RECORD
