Metadata-Version: 2.1
Name: qfadf
Version: 1.0.0
Summary: Quantile Fourier ADF Unit Root Test - Li & Zheng (2018)
Author-email: Dr Merwan Roudane <merwanroudane920@gmail.com>
Maintainer-email: Dr Merwan Roudane <merwanroudane920@gmail.com>
License: MIT License
Project-URL: Homepage, https://github.com/merwanroudane/quantilefourierunitroot
Project-URL: Documentation, https://github.com/merwanroudane/quantilefourierunitroot#readme
Project-URL: Repository, https://github.com/merwanroudane/quantilefourierunitroot
Project-URL: Issues, https://github.com/merwanroudane/quantilefourierunitroot/issues
Project-URL: Changelog, https://github.com/merwanroudane/quantilefourierunitroot/blob/main/CHANGELOG.md
Keywords: econometrics,unit root test,quantile regression,time series,fourier,structural breaks,cointegration,stationarity
Classifier: Development Status :: 5 - Production/Stable
Classifier: Intended Audience :: Science/Research
Classifier: Intended Audience :: Financial and Insurance Industry
Classifier: License :: OSI Approved :: MIT License
Classifier: Operating System :: OS Independent
Classifier: Programming Language :: Python :: 3
Classifier: Programming Language :: Python :: 3.8
Classifier: Programming Language :: Python :: 3.9
Classifier: Programming Language :: Python :: 3.10
Classifier: Programming Language :: Python :: 3.11
Classifier: Programming Language :: Python :: 3.12
Classifier: Topic :: Scientific/Engineering :: Mathematics
Classifier: Topic :: Office/Business :: Financial :: Investment
Classifier: Topic :: Scientific/Engineering :: Information Analysis
Requires-Python: >=3.8
License-File: LICENSE
Requires-Dist: numpy>=1.20.0
Requires-Dist: pandas>=1.3.0
Requires-Dist: scipy>=1.7.0
Provides-Extra: all
Requires-Dist: qfadf[dev,docs,plot]; extra == "all"
Provides-Extra: dev
Requires-Dist: pytest>=7.0.0; extra == "dev"
Requires-Dist: pytest-cov>=3.0.0; extra == "dev"
Requires-Dist: black>=22.0.0; extra == "dev"
Requires-Dist: isort>=5.10.0; extra == "dev"
Requires-Dist: flake8>=4.0.0; extra == "dev"
Requires-Dist: mypy>=0.950; extra == "dev"
Provides-Extra: docs
Requires-Dist: sphinx>=4.0.0; extra == "docs"
Requires-Dist: sphinx-rtd-theme>=1.0.0; extra == "docs"
Requires-Dist: numpydoc>=1.1.0; extra == "docs"
Provides-Extra: plot
Requires-Dist: matplotlib>=3.4.0; extra == "plot"
